jira_assistant/__init__.py
jira_assistant/assistant.py
jira_assistant/console_script.py
jira_assistant/excel_definition.py
jira_assistant/excel_operation.py
jira_assistant/jira_client.py
jira_assistant/milestone.py
jira_assistant/priority.py
jira_assistant/py.typed
jira_assistant/sprint_schedule.py
jira_assistant/story.py
jira_assistant/utils.py
jira_assistant/assets/excel_definition.json
jira_assistant/assets/jira_field_type.json
jira_assistant/assets/sprint_schedule.json
jira_assistant-1.1.5.dist-info/licenses/LICENSE
jira_assistant-1.1.5.dist-info/METADATA
jira_assistant-1.1.5.dist-info/WHEEL
jira_assistant-1.1.5.dist-info/entry_points.txt
jira_assistant-1.1.5.dist-info/top_level.txt
jira_assistant-1.1.5.dist-info/RECORD
