Metadata-Version: 2.4
Name: jira-assistant
Version: 1.1.5
Summary: Connect Excel with Jira
Author-email: Sharry Xu <sharry.xu@outlook.com>
Maintainer-email: Sharry Xu <sharry.xu@outlook.com>
License: MIT License
Project-URL: Documentation, https://jira-assistant.readthedocs.io/en/stable
Project-URL: Repository, https://github.com/jira-assistant/jira-assistant
Project-URL: Issues, https://github.com/jira-assistant/jira-assistant/issues
Keywords: jira,excel,sorting,project management,tool
Classifier: License :: OSI Approved :: MIT License
Classifier: Programming Language :: Python
Classifier: Programming Language :: Python :: 3 :: Only
Classifier: Programming Language :: Python :: 3.10
Classifier: Programming Language :: Python :: 3.11
Classifier: Programming Language :: Python :: 3.12
Classifier: Programming Language :: Python :: 3.13
Classifier: Development Status :: 6 - Mature
Classifier: Intended Audience :: Developers
Classifier: Intended Audience :: Information Technology
Classifier: Intended Audience :: End Users/Desktop
Classifier: License :: OSI Approved :: MIT License
Classifier: Operating System :: MacOS :: MacOS X
Classifier: Operating System :: Microsoft :: Windows
Classifier: Operating System :: POSIX :: Linux
Classifier: Topic :: Software Development :: Libraries
Classifier: Topic :: Software Development :: Libraries :: Python Modules
Classifier: Topic :: Utilities
Classifier: Natural Language :: English
Requires-Python: >=3.10
License-File: LICENSE
Requires-Dist: openpyxl>=3.1.5
Requires-Dist: python-dateutil>=2.9.0
Requires-Dist: python-dotenv>=1.0.1
Requires-Dist: requests>=2.32.3
Requires-Dist: jira>=3.8.0
Requires-Dist: tomli; python_version < "3.11"
Requires-Dist: requests-mock>=1.12.1
Requires-Dist: termcolor>=2.4.0
Provides-Extra: dev
Requires-Dist: pip-tools; extra == "dev"
Requires-Dist: pytest; extra == "dev"
Requires-Dist: pylint; extra == "dev"
Dynamic: license-file
